qq-0.2.1.dist-info/licenses/LICENSE
quickquestion/__init__.py
quickquestion/cache.py
quickquestion/config_app.py
quickquestion/dev_mode.py
quickquestion/llm_lite_provider.py
quickquestion/llm_provider.py
quickquestion/provider_registry.py
quickquestion/qq.py
quickquestion/settings_manager.py
quickquestion/ui_library.py
quickquestion/utils.py
quickquestion/dev_actions/__init__.py
quickquestion/dev_actions/base.py
quickquestion/dev_actions/git_push.py
tests/__init__.py
tests/conftest.py
tests/test_cache.py
tests/test_openai_max_tokens.py
tests/test_prompt.py
tests/test_providers.py
tests/test_qq.py
tests/test_response_parsing.py
tests/test_settings_manager.py
tests/test_simple_mode.py
tests/test_utils.py
qq-0.2.1.dist-info/METADATA
qq-0.2.1.dist-info/WHEEL
qq-0.2.1.dist-info/entry_points.txt
qq-0.2.1.dist-info/top_level.txt
qq-0.2.1.dist-info/RECORD
