Metadata-Version: 2.4
Name: qq
Version: 0.2.1
Summary: A CLI tool for getting quick command-line suggestions using any LLM potentially available
Home-page: https://southbrucke.com
Author: Southbrucke
Author-email: qq@southbrucke.com
License: Proprietary
Classifier: Programming Language :: Python :: 3
Classifier: License :: Other/Proprietary License
Classifier: Operating System :: OS Independent
Classifier: Operating System :: Microsoft :: Windows
Classifier: Operating System :: MacOS
Classifier: Development Status :: 4 - Beta
Classifier: Environment :: Console
Classifier: Topic :: Utilities
Classifier: Topic :: System :: Shells
Classifier: Topic :: Terminals
Classifier: Intended Audience :: Developers
Classifier: Intended Audience :: System Administrators
Classifier: Intended Audience :: End Users/Desktop
Requires-Python: >=3.6
License-File: LICENSE
Requires-Dist: requests>=2.31.0
Requires-Dist: rich>=13.7.0
Requires-Dist: anthropic>=0.18.1
Requires-Dist: aiohttp>=3.9.3
Requires-Dist: colorama>=0.4.6
Requires-Dist: pyperclip>=1.8.2
Requires-Dist: litellm>=1.0.0
Requires-Dist: textual>=0.47.0
Requires-Dist: pywin32>=305; sys_platform == "win32"
Dynamic: author
Dynamic: author-email
Dynamic: classifier
Dynamic: description
Dynamic: description-content-type
Dynamic: home-page
Dynamic: license
Dynamic: license-file
Dynamic: requires-dist
Dynamic: requires-python
Dynamic: summary
